[{"tag":"TITS","size":493.5798471213},{"tag":"BIG","size":417.0531310012},{"tag":"GIRL","size":188.1718567609},{"tag":"HOT","size":171.2241593553},{"tag":"TEEN","size":149.559061641},{"tag":"BUSTY","size":146.9382836917},{"tag":"SEXY","size":132.7860827654},{"tag":"GETS","size":132.7860827654},{"tag":"COCK","size":131.7377715856},{"tag":"BLONDE","size":126.3214971571},{"tag":"PUSSY","size":121.0799412584},{"tag":"FUCKED","size":118.2844447792},{"tag":"FUCKING","size":110.0726738713},{"tag":"FUCK","size":105.0058365026},{"tag":"HUGE","size":98.8906879542},{"tag":"BLACK","size":95.2215988252},{"tag":"JAPANESE","size":94.8721617653},{"tag":"BRUNETTE","size":89.4558873367},{"tag":"BABE","size":85.4373611477},{"tag":"NICE","size":84.389049968}]