[{"tag":"GIRL","size":633.5812133072},{"tag":"ASIAN","size":406.0273972603},{"tag":"AMATEUR","size":254.324853229},{"tag":"WIFE","size":196.3209393346},{"tag":"GIR","size":178.4735812133},{"tag":"SEX","size":174.011741683},{"tag":"FUCK","size":165.0880626223},{"tag":"JAPANESE","size":142.7788649706},{"tag":"COUPLE","size":120.469667319},{"tag":"PUSSY","size":111.5459882583},{"tag":"FUCKED","size":111.5459882583},{"tag":"TITS","size":107.084148728},{"tag":"MASTURBATION","size":107.084148728},{"tag":"PART","size":102.6223091977},{"tag":"COCK","size":93.698630137},{"tag":"FUCKING","size":93.698630137},{"tag":"LOVE","size":89.2367906067},{"tag":"MILF","size":80.313111546},{"tag":"HAIRY","size":75.8512720157},{"tag":"AMP","size":71.3894324853}]